veloce/__init__.py
veloce/client.py
veloce/enums.py
veloce/exceptions.py
veloce/models.py
veloce/retry.py
veloce/api/__init__.py
veloce/api/admin.py
veloce/api/api_keys.py
veloce/api/core.py
veloce/api/inbounds.py
veloce/api/nodes.py
veloce/api/system.py
veloce/api/users.py
veloce_api-1.1.5.dist-info/licenses/LICENSE
veloce_api-1.1.5.dist-info/METADATA
veloce_api-1.1.5.dist-info/WHEEL
veloce_api-1.1.5.dist-info/top_level.txt
veloce_api-1.1.5.dist-info/RECORD
