Metadata-Version: 2.4
Name: veloce-api
Version: 1.1.5
Summary: Python client library for Veloce VPN Panel API
Home-page: https://github.com/ASAPok/veloce-api
Author: ASAPok
License: MIT
Project-URL: Homepage, https://github.com/ASAPok/veloce-api
Project-URL: Repository, https://github.com/ASAPok/veloce-api
Project-URL: Issues, https://github.com/ASAPok/veloce-api/issues
Keywords: veloce,vpn,panel,api,client,xray,v2ray
Classifier: Development Status :: 4 - Beta
Classifier: Intended Audience :: Developers
Classifier: License :: OSI Approved :: MIT License
Classifier: Programming Language :: Python :: 3
Classifier: Programming Language :: Python :: 3.8
Classifier: Programming Language :: Python :: 3.9
Classifier: Programming Language :: Python :: 3.10
Classifier: Programming Language :: Python :: 3.11
Classifier: Programming Language :: Python :: 3.12
Classifier: Topic :: Software Development :: Libraries :: Python Modules
Classifier: Topic :: Internet
Requires-Python: >=3.8
License-File: LICENSE
Requires-Dist: aiohttp>=3.8.0
Requires-Dist: pydantic>=2.0.0
Provides-Extra: dev
Requires-Dist: pytest>=7.0; extra == "dev"
Requires-Dist: pytest-asyncio>=0.21.0; extra == "dev"
Requires-Dist: mypy>=1.0; extra == "dev"
Requires-Dist: black>=23.0; extra == "dev"
Dynamic: home-page
Dynamic: license-file
Dynamic: requires-python
